geomask/__init__.py
geomask-0.1.1.dist-info/LICENSE
geomask-0.1.1.dist-info/METADATA
geomask-0.1.1.dist-info/WHEEL
geomask-0.1.1.dist-info/RECORD
