Metadata-Version: 2.3
Name: geomask
Version: 0.1.1
Summary: A very simple lib for creating geometric masks from spatial data using regular grids
License: MIT
Keywords: gis,spatial,grid,geometry,mask
Author: campiohe
Author-email: campiottihenrique@gmail.com
Requires-Python: >=3.11
Classifier: Development Status :: 4 - Beta
Classifier: Intended Audience :: Science/Research
Classifier: License :: OSI Approved :: MIT License
Classifier: Programming Language :: Python :: 3
Classifier: Programming Language :: Python :: 3.11
Classifier: Programming Language :: Python :: 3.12
Classifier: Topic :: Scientific/Engineering :: GIS
Requires-Dist: shapely (>=2.1.1,<3.0.0)
Project-URL: Homepage, https://github.com/campiohe/geomask
Project-URL: Issues, https://github.com/campiohe/geomask/issues
Project-URL: Repository, https://github.com/campiohe/geomask
